generate_email/__init__.py
generate_email/account_generator.py
generate_email/check_availability.py
generate_email/chrome_driver.py
generate_email/fake_account_data.py
generate_email/proxy_generator.py
generate_email/user_agent_handler.py
generate_email-0.1.0.dist-info/LICENSE
generate_email-0.1.0.dist-info/METADATA
generate_email-0.1.0.dist-info/WHEEL
generate_email-0.1.0.dist-info/top_level.txt
generate_email-0.1.0.dist-info/RECORD
