Metadata-Version: 2.1
Name: generate-email
Version: 0.1.0
Author: Shubham Garg
Author-email: shubham.garg21@outlook.com
License: GPLv3
License-File: LICENSE
Requires-Dist: selenium
Requires-Dist: playwright
Requires-Dist: requests
Requires-Dist: selenium-stealth
Requires-Dist: random-password-generator
Requires-Dist: Faker
Requires-Dist: lxml
Requires-Dist: fake-headers
Requires-Dist: pillow
